aioodbc/__init__.py
aioodbc/connection.py
aioodbc/cursor.py
aioodbc/log.py
aioodbc/pool.py
aioodbc/utils.py
asyncodbc/__init__.py
asyncodbc/connection.py
asyncodbc/cursor.py
asyncodbc/log.py
asyncodbc/pool.py
asyncodbc/utils.py
asyncodbc-0.1.0.dist-info/LICENSE
asyncodbc-0.1.0.dist-info/METADATA
asyncodbc-0.1.0.dist-info/WHEEL
asyncodbc-0.1.0.dist-info/top_level.txt
asyncodbc-0.1.0.dist-info/RECORD
