Metadata-Version: 2.1
Name: asyncodbc
Version: 0.1.0
Summary: ODBC driver for asyncio.
Home-page: https://github.com/tortoise/asyncodbc
Download-URL: https://pypi.python.org/pypi/asyncodbc
Author: Nikolay Novik
Author-email: nickolainovik@gmail.com
License: Apache 2
Platform: POSIX
Classifier: License :: OSI Approved :: Apache Software License
Classifier: Intended Audience :: Developers
Classifier: Programming Language :: Python :: 3
Classifier: Programming Language :: Python :: 3.5
Classifier: Programming Language :: Python :: 3.6
Classifier: Operating System :: POSIX
Classifier: Environment :: Web Environment
Classifier: Development Status :: 3 - Alpha
Classifier: Topic :: Database
Classifier: Topic :: Database :: Front-Ends
Classifier: Framework :: AsyncIO
Requires-Python: >=3.5
License-File: LICENSE
Requires-Dist: pyodbc
